mkdocs_exclude_search/__init__.py
mkdocs_exclude_search/plugin.py
mkdocs_exclude_search/utils.py
mkdocs_exclude_search-0.6.6.dist-info/LICENSE
mkdocs_exclude_search-0.6.6.dist-info/METADATA
mkdocs_exclude_search-0.6.6.dist-info/WHEEL
mkdocs_exclude_search-0.6.6.dist-info/entry_points.txt
mkdocs_exclude_search-0.6.6.dist-info/top_level.txt
mkdocs_exclude_search-0.6.6.dist-info/RECORD
