Metadata-Version: 2.1
Name: mkdocs-exclude-search
Version: 0.6.6
Summary: A mkdocs plugin that lets you exclude selected files or sections from the search index.
Home-page: https://github.com/chrieke/mkdocs-exclude-search
Author: Christoph Rieke
Author-email: christoph.k.rieke@gmail.com
License: MIT
Keywords: mkdocs
Classifier: Development Status :: 5 - Production/Stable
Classifier: Intended Audience :: Developers
Classifier: Intended Audience :: Information Technology
Classifier: License :: OSI Approved :: MIT License
Classifier: Programming Language :: Python
Classifier: Programming Language :: Python :: 3 :: Only
Classifier: Programming Language :: Python :: 3.7
Classifier: Programming Language :: Python :: 3.8
Classifier: Programming Language :: Python :: 3.9
Classifier: Programming Language :: Python :: 3.10
Requires-Python: >=3.6
License-File: LICENSE
